{
  "Flasher": {
    "height": 56.0,
    "pos_x": 1190.979,
    "pos_y": 624.3701,
    "rot_x": 0.0,
    "rot_y": 0.0,
    "rot_z": 0.0,
    "color": "#20ff00",
    "is_timer_enabled": false,
    "timer_interval": 100,
    "name": "bumperhighlight4",
    "image_a": "Flhighlight",
    "image_b": "",
    "alpha": 10000,
    "modulate_vs_add": 0.9,
    "is_visible": true,
    "add_blend": true,
    "is_dmd": false,
    "display_texture": true,
    "depth_bias": 500.0,
    "image_alignment": "wrap",
    "filter": "overlay",
    "filter_amount": 100,
    "light_map": "",
    "drag_points": [
      {
        "x": 526.66394,
        "y": 467.8001,
        "z": 0.0,
        "smooth": false,
        "is_slingshot": false,
        "has_auto_texture": true,
        "tex_coord": 0.0,
        "is_locked": false,
        "editor_layer": 0,
        "editor_layer_name": "",
        "editor_layer_visibility": true
      },
      {
        "x": 526.66394,
        "y": 561.89136,
        "z": 0.0,
        "smooth": false,
        "is_slingshot": false,
        "has_auto_texture": true,
        "tex_coord": 0.0,
        "is_locked": false,
        "editor_layer": 0,
        "editor_layer_name": "",
        "editor_layer_visibility": true
      },
      {
        "x": 622.6636,
        "y": 561.89136,
        "z": 0.0,
        "smooth": false,
        "is_slingshot": false,
        "has_auto_texture": true,
        "tex_coord": 0.0,
        "is_locked": false,
        "editor_layer": 0,
        "editor_layer_name": "",
        "editor_layer_visibility": true
      },
      {
        "x": 622.6636,
        "y": 467.8001,
        "z": 0.0,
        "smooth": false,
        "is_slingshot": false,
        "has_auto_texture": true,
        "tex_coord": 0.0,
        "is_locked": false,
        "editor_layer": 0,
        "editor_layer_name": "",
        "editor_layer_visibility": true
      }
    ]
  }
}